tz_sd/__init__.py
tz_sd/tools.py
tz_sd/tz_sd.py
tz_sd-1.0.1.dist-info/DESCRIPTION.rst
tz_sd-1.0.1.dist-info/METADATA
tz_sd-1.0.1.dist-info/RECORD
tz_sd-1.0.1.dist-info/WHEEL
tz_sd-1.0.1.dist-info/metadata.json
tz_sd-1.0.1.dist-info/top_level.txt
