Metadata-Version: 2.0
Name: tz-sd
Version: 1.0.1
Summary: 该工具主要用于爬虫开发过程中把请求中的参数信息以及头信息转换成dict
Home-page: https://www.shiguangkey.com
Author: QiangZi
Author-email: 6407049@qq.com
License: MIT
Provides-Extra: dev
Requires-Dist: check-manifest; extra == 'dev'
Provides-Extra: test
Requires-Dist: coverage; extra == 'test'
